epages_provisioning/__init__.py
epages_provisioning/features.py
epages_provisioning/provisioning.py
epages_provisioning/shop.py
epages_provisioning/zeep_utils.py
epages_provisioning/data/soap-encodings.xml
epages_provisioning-1.1.4.dist-info/licenses/AUTHORS.rst
epages_provisioning-1.1.4.dist-info/licenses/LICENSE
epages_provisioning-1.1.4.dist-info/METADATA
epages_provisioning-1.1.4.dist-info/WHEEL
epages_provisioning-1.1.4.dist-info/top_level.txt
epages_provisioning-1.1.4.dist-info/RECORD
