Metadata-Version: 2.4
Name: epages_provisioning
Version: 1.1.4
Summary: Python library for calling ePages provisioning services
Home-page: https://github.com/tswfi/epages_provisioning
Author: Tatu Wikman
Author-email: tatu.wikman@gmail.com
License: MIT license
Keywords: epages_provisioning
Classifier: Development Status :: 2 - Pre-Alpha
Classifier: Intended Audience :: Developers
Classifier: License :: OSI Approved :: MIT License
Classifier: Natural Language :: English
Classifier: Programming Language :: Python :: 2.7
Classifier: Programming Language :: Python :: 3.6
License-File: LICENSE
License-File: AUTHORS.rst
Requires-Dist: zeep==4.2.1
Dynamic: author
Dynamic: author-email
Dynamic: classifier
Dynamic: description
Dynamic: description-content-type
Dynamic: home-page
Dynamic: keywords
Dynamic: license
Dynamic: license-file
Dynamic: requires-dist
Dynamic: summary
